[
{"category": "Joyer\u00eda de Fantas\u00eda", "link": "https://www.nihaojewelry.com/es/fashion-jewelry"},
{"category": "Accesorios para pelo", "link": "https://www.nihaojewelry.com/es/hair-accessories"},
{"category": "Bisuter\u00eda Fina", "link": "https://www.nihaojewelry.com/es/fine-jewelry"},
{"category": "Bolsos de Moda", "link": "https://www.nihaojewelry.com/es/fashion-bags"},
{"category": "Relojes de Moda", "link": "https://www.nihaojewelry.com/es/fashion-watches"},
{"category": "Bufandas", "link": "https://www.nihaojewelry.com/es/scarves"},
{"category": "Accesorios de Moda", "link": "https://www.nihaojewelry.com/es/fashion-accessories"},
{"category": "Productos creativos", "link": "https://www.nihaojewelry.com/es/productos-creativos"}
]